MANIFEST.in
README.rst
elophant.py
setup.py
elophant.egg-info/PKG-INFO
elophant.egg-info/SOURCES.txt
elophant.egg-info/dependency_links.txt
elophant.egg-info/requires.txt
elophant.egg-info/top_level.txt