Metadata-Version: 1.0
Name: elophant
Version: 0.0.3
Summary: API Wrapper for Elophant(.com)
Home-page: https://github.com/bryanveloso/elophant.py
Author: Bryan Veloso
Author-email: bryan@revyver.com
License: MIT
Platform: UNKNOWN
